{"id":232,"name":"电子产品、汽车、时尚、收藏品、优惠券及更多 | eBay","url":"https://www.ebay.com","links":"https://www.ebay.com","create_time":"10/29/2023, 9:04:17 PM","update_time":"10/29/2023, 9:04:17 PM","version":"0.5.0","saveThreshold":10,"cloudflare":0,"environment":0,"maxViewLength":15,"recordLog":1,"outputFormat":"xlsx","saveName":"current_time","inputExcel":"","startFromExit":0,"containJudge":false,"desc":"https://www.ebay.com","inputParameters":[{"id":0,"name":"urlList_0","nodeId":1,"nodeName":"Open Page","value":"https://www.ebay.com","desc":"List of URLs to be collected, separated by \\n for multiple lines","type":"text","exampleValue":"https://www.ebay.com"}],"outputParameters":[{"id":0,"name":"para1_text","desc":"","type":"text","recordASField":1,"exampleValue":"主页"},{"id":1,"name":"para2_link_text","desc":"","type":"text","recordASField":1,"exampleValue":"<div class=\"hl-image hl-item__bg-image hl-image__no-fill\"><img src=https://i.ebayimg.com/images/g/zusAAOSwdhxkrsX7/s-l225.webp alt=\"Under Armour 男式 Micro G Valsetz 拉链中筒战术靴\"></div>658.45元"},{"id":2,"name":"para3_link_address","desc":"","type":"text","recordASField":1,"exampleValue":"https://www.ebay.com/itm/225667987522?_trkparms=pageci%3A99e77b5c-765b-11ee-b7d2-f2a02d2dbfdc%7Cparentrq%3A7b888ed918b0acda67a82d3dfffe4a5c%7Ciid%3A1"},{"id":3,"name":"para4_image_address","desc":"","type":"text","recordASField":1,"exampleValue":"https://i.ebayimg.com/images/g/zusAAOSwdhxkrsX7/s-l225.webp"},{"id":4,"name":"para5_text","desc":"","type":"text","recordASField":1,"exampleValue":"<divclass=\"hl-imagehl-item__bg-imagehl-image__no-fill\"><imgsrc=https://i.ebayimg.com/images/g/zusAAOSwdhxkrsX7/s-l225.webpalt=\"UnderArmour男式MicroGValsetz拉链中筒战术靴\"></div>"},{"id":5,"name":"para6_text","desc":"","type":"text","recordASField":1,"exampleValue":"658.45元"},{"id":6,"name":"para7_text","desc":"","type":"text","recordASField":1,"exampleValue":"原先价格:"},{"id":7,"name":"para8_text","desc":"","type":"text","recordASField":1,"exampleValue":"2,253.11元"},{"id":8,"name":"para9_text","desc":"","type":"text","recordASField":1,"exampleValue":"·"},{"id":9,"name":"para10_text","desc":"","type":"text","recordASField":1,"exampleValue":"29%折扣"}],"graph":[{"index":0,"id":0,"parentId":0,"type":-1,"option":0,"title":"root","sequence":[1,2,4],"parameters":{"history":1,"tabIndex":0,"useLoop":false,"xpath":"","iframe":false,"wait":0,"waitType":0,"beforeJS":"","beforeJSWaitTime":0,"afterJS":"","afterJSWaitTime":0,"waitElement":"","waitElementTime":10,"waitElementIframeIndex":0},"isInLoop":false},{"id":1,"index":1,"parentId":0,"type":0,"option":1,"title":"Open Page","sequence":[],"isInLoop":false,"position":0,"parameters":{"useLoop":false,"xpath":"","wait":0,"waitType":0,"beforeJS":"","beforeJSWaitTime":0,"afterJS":"","afterJSWaitTime":0,"waitElement":"","waitElementTime":10,"waitElementIframeIndex":0,"url":"https://www.ebay.com","links":"https://www.ebay.com","maxWaitTime":10,"scrollType":0,"scrollCount":1,"scrollWaitTime":1,"cookies":""}},{"id":2,"index":2,"parentId":0,"type":1,"option":8,"title":"Loop","sequence":[3],"isInLoop":false,"position":1,"parameters":{"history":4,"tabIndex":-1,"useLoop":false,"xpath":"/html/body/div[5]/div[1]/ul[1]/li","iframe":false,"wait":0,"waitType":0,"beforeJS":"","beforeJSWaitTime":0,"afterJS":"","afterJSWaitTime":0,"waitElement":"","waitElementTime":10,"waitElementIframeIndex":0,"scrollType":0,"scrollCount":1,"scrollWaitTime":1,"loopType":1,"pathList":"","textList":"","code":"","waitTime":0,"exitCount":0,"historyWait":2,"breakMode":0,"breakCode":"","breakCodeWaitTime":0,"allXPaths":["/html/body/div[5]/div[1]/ul[1]/li[1]","//li[contains(., '主页')]","//LI[@class='hl-cat-nav__active']","/html/body/div[last()-7]/div[last()-4]/ul/li[last()-12]"]}},{"id":4,"index":3,"parentId":2,"type":0,"option":3,"title":"Collect Data","sequence":[],"isInLoop":true,"position":0,"parameters":{"history":4,"tabIndex":-1,"useLoop":false,"xpath":"","iframe":false,"wait":0,"waitType":0,"beforeJS":"","beforeJSWaitTime":0,"afterJS":"","afterJSWaitTime":0,"waitElement":"","waitElementTime":10,"waitElementIframeIndex":0,"clear":0,"paras":[{"nodeType":0,"contentType":0,"relative":true,"name":"para1_text","desc":"","extractType":0,"relativeXPath":"","allXPaths":"","exampleValues":[{"num":0,"value":"主页"}],"unique_index":"ink5txydetolobhfrvj","iframe":false,"default":"","paraType":"text","recordASField":1,"beforeJS":"","beforeJSWaitTime":0,"JS":"","JSWaitTime":0,"afterJS":"","afterJSWaitTime":0,"downloadPic":0}],"loopType":1}},{"id":3,"index":4,"parentId":0,"type":1,"option":8,"title":"Loop","sequence":[5],"isInLoop":false,"position":2,"parameters":{"history":4,"tabIndex":-1,"useLoop":false,"xpath":"/html/body/div[5]/div[5]/div[2]/div[1]/div[1]/div[1]/div[1]/ul[1]/li","iframe":false,"wait":0,"waitType":0,"beforeJS":"","beforeJSWaitTime":0,"afterJS":"","afterJSWaitTime":0,"waitElement":"","waitElementTime":10,"waitElementIframeIndex":0,"scrollType":0,"scrollCount":1,"scrollWaitTime":1,"loopType":1,"pathList":"","textList":"","code":"","waitTime":0,"exitCount":0,"historyWait":2,"breakMode":0,"breakCode":"","breakCodeWaitTime":0,"allXPaths":["/html/body/div[5]/div[5]/div[2]/div[1]/div[1]/div[1]/div[1]/ul[1]/li[1]","//li[contains(., '<div class')]","//LI[@class='carousel__snap-point hl-carousel__item hl-standard-carousel__item']","/html/body/div[last()-7]/div/div/div/div/div/div/ul/li[last()-14]"]}},{"id":5,"index":5,"parentId":3,"type":0,"option":3,"title":"Collect Data","sequence":[],"isInLoop":true,"position":0,"parameters":{"history":4,"tabIndex":-1,"useLoop":false,"xpath":"","iframe":false,"wait":0,"waitType":0,"beforeJS":"","beforeJSWaitTime":0,"afterJS":"","afterJSWaitTime":0,"waitElement":"","waitElementTime":10,"waitElementIframeIndex":0,"clear":0,"paras":[{"nodeType":1,"contentType":0,"relative":true,"name":"para2_link_text","desc":"","relativeXPath":"/a[1]","allXPaths":["/a[1]","//a[contains(., '<div class')]","//A[@class='hl-item__link']","/html/body/div[last()-7]/div/div/div/div/div/div/ul/li[last()-14]/a"],"exampleValues":[{"num":0,"value":"<div class=\"hl-image hl-item__bg-image hl-image__no-fill\"><img src=https://i.ebayimg.com/images/g/zusAAOSwdhxkrsX7/s-l225.webp alt=\"Under Armour 男式 Micro G Valsetz 拉链中筒战术靴\"></div>658.45元"}],"unique_index":"/a[1]","iframe":false,"default":"","paraType":"text","recordASField":1,"beforeJS":"","beforeJSWaitTime":0,"JS":"","JSWaitTime":0,"afterJS":"","afterJSWaitTime":0,"downloadPic":0},{"nodeType":2,"contentType":0,"relative":true,"name":"para3_link_address","desc":"","relativeXPath":"/a[1]","allXPaths":["/a[1]","//a[contains(., '<div class')]","//A[@class='hl-item__link']","/html/body/div[last()-7]/div/div/div/div/div/div/ul/li[last()-14]/a"],"exampleValues":[{"num":0,"value":"https://www.ebay.com/itm/225667987522?_trkparms=pageci%3A99e77b5c-765b-11ee-b7d2-f2a02d2dbfdc%7Cparentrq%3A7b888ed918b0acda67a82d3dfffe4a5c%7Ciid%3A1"}],"unique_index":"/a[1]","iframe":false,"default":"","paraType":"text","recordASField":1,"beforeJS":"","beforeJSWaitTime":0,"JS":"","JSWaitTime":0,"afterJS":"","afterJSWaitTime":0,"downloadPic":0},{"nodeType":4,"contentType":1,"relative":true,"name":"para4_image_address","desc":"","relativeXPath":"/a[1]/div[1]/img[1]","allXPaths":["/a[1]/div[1]/img[1]","//img[contains(., '')]","//IMG[@alt='Under Armour 男式 Micro G Valsetz 拉链中筒战术靴']","/html/body/div[last()-7]/div/div/div/div/div/div/ul/li[last()-14]/a/div[last()-1]/img"],"exampleValues":[{"num":0,"value":"https://i.ebayimg.com/images/g/zusAAOSwdhxkrsX7/s-l225.webp"}],"unique_index":"/a[1]/div[1]/img[1]","iframe":false,"default":"","paraType":"text","recordASField":1,"beforeJS":"","beforeJSWaitTime":0,"JS":"","JSWaitTime":0,"afterJS":"","afterJSWaitTime":0,"downloadPic":0},{"nodeType":0,"contentType":1,"relative":true,"name":"para5_text","desc":"","relativeXPath":"/a[1]/noscript[1]","allXPaths":["/a[1]/noscript[1]","//noscript[contains(., '<div class')]","/html/body/div[last()-7]/div/div/div/div/div/div/ul/li[last()-14]/a/noscript"],"exampleValues":[{"num":0,"value":"<divclass=\"hl-imagehl-item__bg-imagehl-image__no-fill\"><imgsrc=https://i.ebayimg.com/images/g/zusAAOSwdhxkrsX7/s-l225.webpalt=\"UnderArmour男式MicroGValsetz拉链中筒战术靴\"></div>"}],"unique_index":"/a[1]/noscript[1]","iframe":false,"default":"","paraType":"text","recordASField":1,"beforeJS":"","beforeJSWaitTime":0,"JS":"","JSWaitTime":0,"afterJS":"","afterJSWaitTime":0,"downloadPic":0},{"nodeType":0,"contentType":1,"relative":true,"name":"para6_text","desc":"","relativeXPath":"/a[1]/div[2]/span[1]","allXPaths":["/a[1]/div[2]/span[1]","//span[contains(., '658.45元')]","//SPAN[@class='hl-item__displayPrice']","/html/body/div[last()-7]/div/div/div/div/div/div/ul/li[last()-14]/a/div/span"],"exampleValues":[{"num":0,"value":"658.45元"}],"unique_index":"/a[1]/div[2]/span[1]","iframe":false,"default":"","paraType":"text","recordASField":1,"beforeJS":"","beforeJSWaitTime":0,"JS":"","JSWaitTime":0,"afterJS":"","afterJSWaitTime":0,"downloadPic":0},{"nodeType":0,"contentType":1,"relative":true,"name":"para7_text","desc":"","relativeXPath":"/a[1]/div[3]/span[1]/span[1]","allXPaths":["/a[1]/div[3]/span[1]/span[1]","//span[contains(., '原先价格:')]","//SPAN[@class='clipped']","/html/body/div[last()-7]/div/div/div/div/div/div/ul/li[last()-11]/a/div/span[last()-2]/span"],"exampleValues":[{"num":3,"value":"原先价格:"}],"unique_index":"/a[1]/div[3]/span[1]/span[1]","iframe":false,"default":"","paraType":"text","recordASField":1,"beforeJS":"","beforeJSWaitTime":0,"JS":"","JSWaitTime":0,"afterJS":"","afterJSWaitTime":0,"downloadPic":0},{"nodeType":0,"contentType":1,"relative":true,"name":"para8_text","desc":"","relativeXPath":"/a[1]/div[3]/span[1]/del[1]","allXPaths":["/a[1]/div[3]/span[1]/del[1]","//del[contains(., '2,253.11元')]","/html/body/div[last()-7]/div/div/div/div/div/div/ul/li[last()-11]/a/div/span[last()-2]/del"],"exampleValues":[{"num":3,"value":"2,253.11元"}],"unique_index":"/a[1]/div[3]/span[1]/del[1]","iframe":false,"default":"","paraType":"text","recordASField":1,"beforeJS":"","beforeJSWaitTime":0,"JS":"","JSWaitTime":0,"afterJS":"","afterJSWaitTime":0,"downloadPic":0},{"nodeType":0,"contentType":1,"relative":true,"name":"para9_text","desc":"","relativeXPath":"/a[1]/div[3]/span[2]","allXPaths":["/a[1]/div[3]/span[2]","//span[contains(., '·')]","//SPAN[@class='hl-item__separator']","/html/body/div[last()-7]/div/div/div/div/div/div/ul/li[last()-11]/a/div/span[last()-1]"],"exampleValues":[{"num":3,"value":"·"}],"unique_index":"/a[1]/div[3]/span[2]","iframe":false,"default":"","paraType":"text","recordASField":1,"beforeJS":"","beforeJSWaitTime":0,"JS":"","JSWaitTime":0,"afterJS":"","afterJSWaitTime":0,"downloadPic":0},{"nodeType":0,"contentType":1,"relative":true,"name":"para10_text","desc":"","relativeXPath":"/a[1]/div[3]/span[3]/strong[1]","allXPaths":["/a[1]/div[3]/span[3]/strong[1]","//strong[contains(., '29% 折扣')]","/html/body/div[last()-7]/div/div/div/div/div/div/ul/li[last()-11]/a/div/span/strong"],"exampleValues":[{"num":3,"value":"29%折扣"}],"unique_index":"/a[1]/div[3]/span[3]/strong[1]","iframe":false,"default":"","paraType":"text","recordASField":1,"beforeJS":"","beforeJSWaitTime":0,"JS":"","JSWaitTime":0,"afterJS":"","afterJSWaitTime":0,"downloadPic":0}]}}]}