{"id":29,"name":"BigSpy","url":"https://bigspy.com/adspy/facebook/?app_type=3","links":"https://bigspy.com/adspy/facebook/?app_type=3","create_time":"6/2/2023, 10:20:57 PM","version":"0.3.2","containJudge":false,"desc":"https://bigspy.com/adspy/facebook/?app_type=3","inputParameters":[{"id":0,"name":"urlList_0","nodeId":1,"nodeName":"打开网页","value":"https://bigspy.com/adspy/facebook/?app_type=3","desc":"要采集的网址列表，多行以\\n分开","type":"string","exampleValue":"https://bigspy.com/adspy/facebook/?app_type=3"}],"outputParameters":[],"graph":[{"index":0,"id":0,"parentId":0,"type":-1,"option":0,"title":"root","sequence":[1],"parameters":{"history":1,"tabIndex":0,"useLoop":false,"xpath":"","wait":0},"isInLoop":false},{"id":1,"index":1,"parentId":0,"type":0,"option":1,"title":"打开网页","sequence":[],"isInLoop":false,"position":0,"parameters":{"useLoop":false,"xpath":"","wait":500,"beforeJS":"","beforeJSWaitTime":0,"afterJS":"","afterJSWaitTime":0,"url":"https://bigspy.com/adspy/facebook/?app_type=3","links":"https://bigspy.com/adspy/facebook/?app_type=3","maxWaitTime":10,"scrollType":0,"scrollCount":1,"scrollWaitTime":1}}]}